calllib.py
calllib-1.8.dist-info/DESCRIPTION.rst
calllib-1.8.dist-info/METADATA
calllib-1.8.dist-info/RECORD
calllib-1.8.dist-info/WHEEL
calllib-1.8.dist-info/metadata.json
calllib-1.8.dist-info/top_level.txt
